protect_my_dir/__init__.py
protect_my_dir/main.py
protect_my_dir/py.typed
protect_my_dir-0.1.1.dist-info/licenses/LICENSE
protect_my_dir-0.1.1.dist-info/METADATA
protect_my_dir-0.1.1.dist-info/WHEEL
protect_my_dir-0.1.1.dist-info/entry_points.txt
protect_my_dir-0.1.1.dist-info/top_level.txt
protect_my_dir-0.1.1.dist-info/RECORD
