Metadata-Version: 2.4
Name: protect-my-dir
Version: 0.1.1
Summary: Simple python project to encrypt files and require a password to access them.
Author-email: John Aziz <johnaziz269@gmail.com>
Maintainer-email: John Aziz <johnaziz269@gmail.com>
License: MIT License
Project-URL: Homepage, https://github.com/john0isaac/protect-my-dir
Project-URL: Issues, https://github.com/john0isaac/protect-my-dir/issues
Project-URL: Contributing, https://github.com/john0isaac/protect-my-dir/pulls
Project-URL: Releases, https://github.com/john0isaac/protect-my-dir/releases
Classifier: Development Status :: 5 - Production/Stable
Classifier: Environment :: Console
Classifier: License :: OSI Approved :: MIT License
Classifier: Operating System :: OS Independent
Classifier: Programming Language :: Python
Classifier: Programming Language :: Python :: 3 :: Only
Classifier: Programming Language :: Python :: 3.10
Classifier: Programming Language :: Python :: 3.11
Classifier: Programming Language :: Python :: 3.12
Classifier: Topic :: Software Development :: Libraries :: Python Modules
Classifier: Topic :: Software Development :: Quality Assurance
Requires-Python: >=3.10
License-File: LICENSE
Requires-Dist: click>=8.1.8
Requires-Dist: cryptography>=44.0.2
Provides-Extra: dev
Requires-Dist: pre-commit; extra == "dev"
Requires-Dist: mypy; extra == "dev"
Requires-Dist: types-requests; extra == "dev"
Provides-Extra: lint
Requires-Dist: ruff; extra == "lint"
Provides-Extra: test
Requires-Dist: pytest; extra == "test"
Requires-Dist: pytest-cov; extra == "test"
Provides-Extra: docs
Requires-Dist: mkdocs; extra == "docs"
Requires-Dist: mkdocs-material; extra == "docs"
Requires-Dist: mkdocstrings[python]; extra == "docs"
Requires-Dist: pymdown-extensions; extra == "docs"
Dynamic: license-file
